{"is_source_file": true, "format": "TypeScript", "description": "This file serves as the entry point for a Remotion project, importing the root component and registering it as the main React root.", "external_files": ["./Root"], "external_methods": ["registerRoot"], "published": ["registerRoot"], "classes": [], "methods": [{"name": "registerRoot", "description": "Function imported from 'remotion' to register the root React component for rendering."}], "calls": ["registerRoot(RemotionRoot)"], "search-terms": ["remotion", "registerRoot", "entry", "index.ts", "Root"], "state": 2, "file_id": 614, "knowledge_revision": 1638, "git_revision": "1aee8ed1eca8330cc765b711c43546e90b04ff39", "ctags": [], "hash": "6c2ce436880cb16c98160769ed0f6150", "format-version": 4, "code-base-name": "universalinit", "filename": "src/universalinit/templates/remotion/src/index.ts", "revision_history": [{"1638": "1aee8ed1eca8330cc765b711c43546e90b04ff39"}]}