{"is_source_file": true, "format": "TypeScript/TSX", "description": "This file defines the root layout component for a Remix.run web application using React. It sets up external links to stylesheets, and provides the main app structure including meta tags, links, outlet rendering, and scripts.", "external_files": ["@remix-run/react", "@remix-run/node", "./tailwind.css"], "external_methods": ["Links", "Meta", "Outlet", "Scripts", "ScrollRestoration", "LinksFunction"], "published": ["links", "Layout", "App"], "classes": [], "methods": [{"name": "links", "description": "Defines external links and preconnects for stylesheets and fonts used in the layout."}, {"name": "Layout", "description": "React functional component that provides the HTML skeleton and layout structure."}, {"name": "App", "description": "Main React component rendering the Outlet for nested routes."}], "calls": ["React.createElement", "Meta()", "Links()", "ScrollRestoration()", "Scripts()", "Outlet()"], "search-terms": ["remix", "root layout", "app component", "react outlet", "tailwind"], "state": 2, "file_id": 585, "knowledge_revision": 1607, "git_revision": "1aee8ed1eca8330cc765b711c43546e90b04ff39", "ctags": [], "hash": "ecb43bd0ae9b4e549b896a93f472a193", "format-version": 4, "code-base-name": "universalinit", "filename": "src/universalinit/templates/remix/app/root.tsx", "revision_history": [{"1607": "1aee8ed1eca8330cc765b711c43546e90b04ff39"}]}