{"is_source_file": true, "format": "bash", "description": "This is a shell script that automates starting and configuring a MongoDB server, including checks for existing instances, setup of users, database, and environment variables.", "external_files": ["db_connection.txt", "db_visualizer/mongodb.env", "/var/lib/mongodb/mongod.log"], "external_methods": ["mongosh", "pgrep", "lsof", "pkill", "sleep"], "published": ["MONGODB_URL", "MONGODB_DB"], "classes": [], "methods": [], "calls": ["mongosh --port ${DB_PORT} --eval \"db.adminCommand('ping')\"", "pgrep -x mongod", "sudo lsof -Pan -p $MONGO_PID -i", "sudo pkill -x mongod", "sleep 2", "nohup sudo mongod --dbpath /var/lib/mongodb --port ${DB_PORT} --bind_ip 127.0.0.1 --unixSocketPrefix /var/run/mongodb", "mongosh --port ${DB_PORT}", "use admin", "db.getUser", "db.createUser", "use ${DB_NAME}", "db.getUser", "print", "cat > db_visualizer/mongodb.env", "echo", "source db_visualizer/mongodb.env", "cat db_connection.txt"], "search-terms": ["mongodb", "startup.sh", "shell script", "mongosh", "database setup"], "state": 2, "file_id": 420, "knowledge_revision": 1442, "git_revision": "1aee8ed1eca8330cc765b711c43546e90b04ff39", "hash": "a5cffa3a0c62b0ad3e0a1886acab1420", "format-version": 4, "code-base-name": "universalinit", "filename": "src/universalinit/templates/mongodb/startup.sh", "revision_history": [{"1442": "1aee8ed1eca8330cc765b711c43546e90b04ff39"}]}