{"is_source_file": true, "format": "TypeScript/TSX", "description": "A React functional component named Subtitle that displays a styled subtitle with animated opacity based on the current frame, used in a Remotion video project.", "external_files": ["./constants"], "external_methods": ["interpolate", "useCurrentFrame"], "published": ["Subtitle"], "classes": [], "methods": [{"name": "Subtitle", "description": "React functional component that renders a subtitle with animated opacity."}], "calls": ["useCurrentFrame", "interpolate"], "search-terms": ["Subtitle", "Remotion", "React", "animation", "frame-based opacity", "TSX", "video subtitle"], "state": 2, "file_id": 253, "knowledge_revision": 593, "git_revision": "94781c9538a488e1e0d0eedb4c9b28700e40616c", "ctags": [], "filename": "src/universalinit/templates/remotion/src/HelloWorld/Subtitle.tsx", "hash": "a4a6f5bec7582a30b3d43db862a5acf7", "format-version": 4, "code-base-name": "https://github.com/Kavia-ai/universalinit.git:main", "revision_history": [{"593": "94781c9538a488e1e0d0eedb4c9b28700e40616c"}]}