{"is_source_file": true, "description": "Simple json file", "external_files": [], "external_methods": [], "published": [], "calls": [], "search-terms": [], "classes": [], "methods": [], "state": 2, "file_id": 329, "knowledge_revision": 671, "git_revision": "ca4234c1ba905df46cb271e20dea9ad53ab41797", "filename": "src/universalinit/templates/react/public/manifest.json", "hash": "d9d975cebe2ec20b6c652e1e4c12ccf0", "format-version": 4, "code-base-name": "https://github.com/Kavia-ai/universalinit.git:main", "revision_history": [{"671": "ca4234c1ba905df46cb271e20dea9ad53ab41797"}]}