{"is_source_file": true, "format": "TypeScript", "description": "This file is a configuration script for the remotion video rendering library, setting specific configuration options such as image format and output overwrite behavior.", "external_files": ["@remotion/cli/config"], "external_methods": ["Config.setVideoImageFormat", "Config.setOverwriteOutput"], "published": [], "classes": [], "methods": [{"name": "setVideoImageFormat", "description": "Sets the video image format, here configured as JPEG."}, {"name": "setOverwriteOutput", "description": "Configures whether to overwrite existing output files, here set to true."}], "calls": ["Config.setVideoImageFormat(\"jpeg\")", "Config.setOverwriteOutput(true)"], "search-terms": ["remotion.config.ts", "Remotion", "Config", "setVideoImageFormat", "setOverwriteOutput", "jpeg", "Configuration"], "state": 2, "file_id": 389, "knowledge_revision": 1411, "git_revision": "1aee8ed1eca8330cc765b711c43546e90b04ff39", "ctags": [], "hash": "59c56da67f1bfdb377d7df8bd4fadc25", "format-version": 4, "code-base-name": "universalinit", "filename": "src/universalinit/templates/remotion/remotion.config.ts", "revision_history": [{"1411": "1aee8ed1eca8330cc765b711c43546e90b04ff39"}]}