{"is_source_file": true, "format": "TypeScript/TSX", "description": "This file is a server-side entry point for a Remix application, handling HTTP requests and rendering server responses with streaming support, including bot detection and CORS headers.", "external_files": ["@remix-run/node", "@remix-run/react", "isbot", "react-dom/server"], "external_methods": ["createReadableStreamFromReadable", "renderToPipeableStream", "PassThrough"], "published": ["handleRequest"], "classes": [], "methods": [{"name": "handleRequest", "description": "Main request handler that sets CORS headers, detects bots, and delegates to specific request handling functions."}, {"name": "handleBotRequest", "description": "Handles requests from bots, streaming the server-rendered React app."}, {"name": "handleBrowserRequest", "description": "Handles requests from browsers, streaming the server-rendered React app."}], "calls": ["renderToPipeableStream", "createReadableStreamFromReadable", "PassThrough", "setTimeout", "console.error"], "search-terms": ["remix server entry", "streaming server response", "bot detection", "react-dom server", "remix request handler"], "state": 2, "file_id": 241, "knowledge_revision": 586, "git_revision": "4fcd6aab2fc7e923668b4fb3f5b78e27dbb79d9a", "ctags": [], "filename": "src/universalinit/templates/remix/app/entry.server.tsx", "hash": "ea3fdec8a39ab86ca67d22f9ecc48c65", "format-version": 4, "code-base-name": "https://github.com/Kavia-ai/universalinit.git:main", "revision_history": [{"586": "4fcd6aab2fc7e923668b4fb3f5b78e27dbb79d9a"}]}