{"is_source_file": true, "format": "TypeScript (TSX)", "description": "This file defines a Qwik component called RouterHead, which renders content inside the document's <head> element, including dynamic title, meta, link, style, and script tags based on the document head data.", "external_files": ["@builder.io/qwik", "@builder.io/qwik-city"], "external_methods": ["useDocumentHead", "useLocation", "component$"], "published": ["RouterHead"], "classes": [], "methods": [{"name": "RouterHead", "description": "A Qwik component that generates document head elements dynamically based on provided document head data."}], "calls": ["useDocumentHead()", "useLocation()"], "search-terms": ["Qwik", "RouterHead", "document head", "useDocumentHead", "useLocation", "head meta", "head links", "head styles", "head scripts"], "state": 2, "file_id": 395, "knowledge_revision": 1075, "git_revision": "1aee8ed1eca8330cc765b711c43546e90b04ff39", "ctags": [], "hash": "822ca7bb4d7b877473e28386699dbe73", "format-version": 4, "code-base-name": "universalinit", "filename": "src/universalinit/templates/qwik/src/components/router-head/router-head.tsx", "revision_history": [{"1075": "1aee8ed1eca8330cc765b711c43546e90b04ff39"}]}