{"is_source_file": false, "format": "", "description": "", "external_files": [], "external_methods": [], "published": [], "classes": [], "methods": [], "calls": [], "search-terms": [], "state": 2, "file_id": 345, "knowledge_revision": 730, "git_revision": "67e5b3ebfcb2f1a495fbaf77f3efc93a0881a9ab", "hash": "806eeecd1f9b30d3af064ea8984f68d2", "format-version": 4, "code-base-name": "universalinit", "filename": "src/universalinit/templates/vue/README.md", "revision_history": [{"730": "67e5b3ebfcb2f1a495fbaf77f3efc93a0881a9ab"}]}