{"is_source_file": true, "format": "JavaScript module (.mjs)", "description": "ESLint configuration file for React projects, defining environment, parser options, globals, and rules.", "external_files": ["@eslint/js", "eslint-plugin-react"], "external_methods": ["pluginJs", "pluginReact.configs.recommended"], "published": [], "classes": [], "methods": [], "calls": ["pluginJs.configs.recommended", "pluginReact"], "search-terms": ["eslint", "react", "jsx", "eslint.config.mjs", "parserOptions", "globals", "rules"], "state": 2, "file_id": 365, "knowledge_revision": 759, "git_revision": "6aed84d41ab509d04604ae7f75ac55717f79a752", "hash": "be6538e7523bc2e9da0743133d784136", "format-version": 4, "code-base-name": "universalinit", "filename": "src/universalinit/templates/react/eslint.config.mjs", "revision_history": [{"759": "6aed84d41ab509d04604ae7f75ac55717f79a752"}]}