{"is_source_file": false, "format": "", "description": "", "external_files": [], "external_methods": [], "published": [], "classes": [], "methods": [], "calls": [], "search-terms": [], "state": 2, "file_id": 309, "knowledge_revision": 697, "git_revision": "5ad3129c17dcf7bb8c500a724b669269149cb53d", "hash": "582a579a0bca0091030c5064eeec0e96", "format-version": 4, "code-base-name": "universalinit", "filename": "src/universalinit/templates/flutter/analysis_options.yaml", "revision_history": [{"697": "5ad3129c17dcf7bb8c500a724b669269149cb53d"}]}