{"is_source_file": true, "format": "bash script", "description": "A shell script that automates the creation of a new Android project structure, including directory setup, resource placeholders, build configuration files, and template source code.", "external_files": ["gradle/wrapper/gradle-wrapper.jar", "gradle/wrapper/gradle-wrapper.properties", "settings.gradle", "build.gradle", "gradlew", "app/build.gradle", "app/src/main/AndroidManifest.xml", "app/src/main/java/<package_path>/MainActivity.java", "app/src/main/res/layout/activity_main.xml", "app/src/main/res/values/strings.xml", "app/src/main/res/mipmap-xxhdpi/ic_launcher.png", "app/src/main/res/mipmap-hdpi/ic_launcher.png", "app/src/main/res/mipmap-xhdpi/ic_launcher.png", "app/src/main/res/mipmap-xxxhdpi/ic_launcher.png", "app/src/main/res/mipmap-mdpi/ic_launcher.png", "app/src/main/res/mipmap-mdpi/ic_launcher_round.png", "gradle.properties"], "external_methods": ["tr", "sed", "echo", "mkdir", "curl", "chmod", "base64"], "published": ["PROJECT_NAME", "PACKAGE_NAME", "MIN_SDK", "TARGET_SDK", "COMPILE_SDK", "GRADLE_VERSION"], "classes": [], "methods": [], "calls": ["echo", "mkdir", "sed", "tr", "base64", "curl"], "search-terms": ["android project setup", "bash automation script", "project directory creation", "Gradle configuration", "AndroidManifest", "MainActivity", "resource placeholders"], "state": 2, "file_id": 371, "knowledge_revision": 1389, "git_revision": "1aee8ed1eca8330cc765b711c43546e90b04ff39", "hash": "3410249d4a47a7d965dc785659513c62", "format-version": 4, "code-base-name": "universalinit", "filename": "src/universalinit/templates/android/init_script.sh", "revision_history": [{"1389": "1aee8ed1eca8330cc765b711c43546e90b04ff39"}]}